openprotein/__init__.py
openprotein/core/__init__.py
openprotein/core/config.py
openprotein/core/rule.py
openprotein/core/setup.py
openprotein/data/__init__.py
openprotein/data/factory.py
openprotein/data/process.py
openprotein/datasets/__init__.py
openprotein/datasets/ec.py
openprotein/datasets/flip.py
openprotein/datasets/go.py
openprotein/datasets/tape.py
openprotein/datasets/uniref.py
openprotein/models/__init__.py
openprotein/models/esm1b.py
openprotein/models/gearnet.py
openprotein/models/proteinbert.py
openprotein/piplines/Pipline.py
openprotein/piplines/Trainer.py
openprotein/piplines/__init__.py
openprotein/task/__init__.py
openprotein/task/ec.py
openprotein/task/flip.py
openprotein/task/tape.py
openprotein/utils/__init__.py
openprotein/utils/activation.py
openprotein/utils/metrics.py
openprotein/utils/utils.py
openprotein-0.2.0.dist-info/LICENSE
openprotein-0.2.0.dist-info/METADATA
openprotein-0.2.0.dist-info/WHEEL
openprotein-0.2.0.dist-info/top_level.txt
openprotein-0.2.0.dist-info/RECORD
